{
  "document_version": 3,
  "product_revision": 3,
  "content_hash": "6bb46f638ad6",
  "generated_at": "2026-07-23 01:49 UTC",
  "snapshot": {
    "identity": {
      "model_no": "A24-005-AR-V5-NVME-S",
      "upc_ean": "5065019946164",
      "dimensions_cm": "10.00 x 4.00 x 16.50 cm",
      "weight_kg": "0.355",
      "category": "ONE v5",
      "hts_code": "8473.30.5100"
    },
    "specs": {
      "case_material": "Injected aluminum alloy top and injected ABS plastic bottom",
      "cooling_fan": "Blower type 30mm PWM actively controlled by the Raspberry Pi OS",
      "audio_dac": "HS100B - DAC Chip",
      "audio_connectivity": "3.5mm audio out and mic in",
      "usb_hub_chip": "FE1.1S - USB Hub Chip",
      "front_usb_2_0_ports": "2",
      "hdmi_conversion": "Converted the micro HDMI of the RPi 5 to Regular HDMI",
      "gpio_access": "Full GPIO Access with Magnetic cover",
      "nvme_form_factors_supported": "2230, 2242, 2260, 2280",
      "single_drive_variant": "RPI 5 Native 1 PCIe Gen2",
      "dual_gen2_chip": "ASM1182e - 1 PCIe x1 Gen2 upstream port to 2 PCIe x 1 Gen2 downstream ports",
      "dual_quad_gen3_chip": "ASM2806 PCIe Gen3 Packet Switching Chips",
      "oled_module_size": "1.8 inch",
      "zigbee_chip": "CC2562P",
      "nvme_ssd_options": "128 GB M.2 NVMe SSD, 256 GB M.2 NVMe SSD",
      "recommended_power_supply": "Argon PWR GaN 27W Power Delivery",
      "recommended_ups": "Argon PWR UPS for Argon ONE V5 27W PD",
      "fan": "Blower type 30mm PWM",
      "fan_control": "actively controlled by the Raspberry Pi OS",
      "audio_ports": "3.5mm audio out and mic in",
      "hdmi_ports": "2 Regular HDMI",
      "original_ports": "micro HDMI of the RPi 5",
      "compatible_board": "Raspberry Pi 5",
      "optional_storage": "M.2 NVMe-PCIe Expansion Boards with THRML Cooling",
      "optional_oled": "1.8 inch OLED Module",
      "optional_zigbee": "CC2562P Zigbee Chip for Home Assistant",
      "power_input": "USB-C",
      "product_name": "Argon Industrial V5 ZigBEE Module",
      "dimensions": "110mmx90mm",
      "compatible_case": "Argon ONE V5",
      "supported_os": "Home Assistant OS",
      "supported_raspberry_pi": "Raspberry Pi 5",
      "product": "Argon Industrial V5 OLED Module",
      "oled_dimensions": "55mmx90mm",
      "gpio_pins_required": "first 8 GPIO pins",
      "material": "Aluminum alloy",
      "m2_slot": "M.2 NVMe PCIe, 2230/2242/2280",
      "gpio": "40-pin passthrough header",
      "hdmi": "2x full-size HDMI",
      "power_button": "Programmable, supports safe shutdown"
    },
    "compatibility": [
      "Raspberry Pi 5"
    ],
    "description": "Aluminum Raspberry Pi 5 case with M.2 NVMe SSD slot via PCIe for maximum storage performance.",
    "features": [
      "M.2 NVMe SSD slot (PCIe, 2230/2242/2280)",
      "Full-size HDMI ports (2x)",
      "PWM-controlled fan",
      "Programmable power button",
      "40-pin GPIO passthrough header"
    ]
  },
  "history": [
    {
      "document_version": 1,
      "product_revision": 1,
      "generated_at": "2026-07-23 00:51 UTC",
      "data_changed": true,
      "remarks": [
        "Initial datasheet — all fields new."
      ]
    },
    {
      "document_version": 2,
      "product_revision": 2,
      "generated_at": "2026-07-23 01:10 UTC",
      "data_changed": true,
      "remarks": [
        "Added spec `antenna_type` = screw-on antenna",
        "Added spec `chip` = CHIP2102N",
        "Added spec `compatible_board` = Raspberry Pi 5",
        "Added spec `compatible_raspberry_pi` = Raspberry Pi 5",
        "Removed spec `cooling_fan`",
        "Removed spec `cooling_type`",
        "Added spec `display_type` = OLED",
        "Added spec `dual_gen2_chip` = ASM1182e",
        "Removed spec `dual_gen2_chipset`",
        "Added spec `dual_gen2_ports` = 1 PCIe x1 Gen2 upstream port to 2 PCIe x 1 Gen2 downstream ports",
        "Removed spec `dual_gen3_chipset`",
        "Removed spec `ethernet`",
        "Added spec `ethernet_port` = 1",
        "spec `fan`: PWM, software-controlled → Blower type 30mm PWM",
        "Added spec `fan_control` = actively controlled by the Raspberry Pi OS",
        "Removed spec `fan_size`",
        "Added spec `front_usb2_ports` = 2",
        "Removed spec `front_usb_2_0_ports`",
        "Added spec `front_usb_ports` = 2x USB 2.0 ports",
        "Added spec `gpio_pins_required` = first 8 GPIO pins",
        "Removed spec `gpio_pins_used`",
        "Added spec `hdmi_conversion` = Converted the micro HDMI of the RPi 5 to Regular HDMI",
        "Removed spec `max_nvme_drives`",
        "Removed spec `nvme_form_factors_supported`",
        "Added spec `nvme_size_compatibility` = 2230, 2242, 2260, 2280",
        "Removed spec `oled_dimensions`",
        "Added spec `oled_module` = 1.8 inch OLED Module",
        "spec `power_input`: USB-C Power Input → USB-C",
        "Added spec `product` = Argon Industrial V5 OLED Module",
        "Added spec `quad_gen3_chip` = ASM2806",
        "Removed spec `quad_gen3_chipset`",
        "Added spec `screws_flat_head` = 8 pcs Flat head 2.5x6",
        "Added spec `screws_round_head` = 4 pcs Round head 2.5x8",
        "Removed spec `single_drive_chipset`",
        "Added spec `single_nvme_variant` = RPI 5 Native 1 PCIe Gen2",
        "spec `ssd_options`: 128 GB M.2 NVMe SSD, 256 GB M.2 NVMe SSD → 128 GB, 256 GB M.2 NVMe SSD",
        "Removed spec `supported_os`",
        "Removed spec `supported_raspberry_pi`",
        "Added spec `usb3_ports` = 2",
        "Removed spec `usb_3_0_ports`",
        "spec `usb_hub_chip`: FE1.1S → FE1.1S - USB Hub Chip",
        "Added spec `wireless_protocol` = ZigBEE",
        "Added spec `zigbee_compatibility` = Fully compatible with Home Assistant Operating System"
      ]
    },
    {
      "document_version": 3,
      "product_revision": 3,
      "generated_at": "2026-07-23 01:49 UTC",
      "data_changed": true,
      "remarks": [
        "Removed spec `antenna_type`",
        "Added spec `audio_connectivity` = 3.5mm audio out and mic in",
        "Removed spec `chip`",
        "Removed spec `compatible_raspberry_pi`",
        "Added spec `cooling_fan` = Blower type 30mm PWM actively controlled by the Raspberry Pi OS",
        "Removed spec `display_type`",
        "spec `dual_gen2_chip`: ASM1182e → ASM1182e - 1 PCIe x1 Gen2 upstream port to 2 PCIe x 1 Gen2 downstream ports",
        "Removed spec `dual_gen2_ports`",
        "Added spec `dual_quad_gen3_chip` = ASM2806 PCIe Gen3 Packet Switching Chips",
        "Removed spec `ethernet_port`",
        "Removed spec `front_usb2_ports`",
        "Added spec `front_usb_2_0_ports` = 2",
        "Removed spec `front_usb_ports`",
        "Removed spec `nvme_expansion_options`",
        "Added spec `nvme_form_factors_supported` = 2230, 2242, 2260, 2280",
        "Removed spec `nvme_size_compatibility`",
        "Added spec `nvme_ssd_options` = 128 GB M.2 NVMe SSD, 256 GB M.2 NVMe SSD",
        "Added spec `oled_dimensions` = 55mmx90mm",
        "Removed spec `oled_module`",
        "Added spec `optional_oled` = 1.8 inch OLED Module",
        "Added spec `optional_storage` = M.2 NVMe-PCIe Expansion Boards with THRML Cooling",
        "Added spec `optional_zigbee` = CC2562P Zigbee Chip for Home Assistant",
        "Added spec `original_ports` = micro HDMI of the RPi 5",
        "Removed spec `quad_gen3_chip`",
        "Removed spec `screws_flat_head`",
        "Removed spec `screws_round_head`",
        "Added spec `single_drive_variant` = RPI 5 Native 1 PCIe Gen2",
        "Removed spec `single_nvme_variant`",
        "Removed spec `ssd_options`",
        "Added spec `supported_os` = Home Assistant OS",
        "Added spec `supported_raspberry_pi` = Raspberry Pi 5",
        "Removed spec `usb3_ports`",
        "Removed spec `wireless_protocol`",
        "Removed spec `zigbee_compatibility`"
      ]
    }
  ]
}